[{"type":"user","text":"Scan printer","errorNode":null},{"type":"decision","text":"Scanned value exists in NKP IP table?","errorNode":{"text":"ERROR: Invalid printer"}},{"type":"user","text":"Scan check sheet (M* barcode)","errorNode":null},{"type":"decision","text":"Scanned value starts with \"M\"?","errorNode":{"text":"ERROR: Incorrect check sheet format."}},{"type":"decision","text":"Scanned value exists in the EOX Check Sheet table?","errorNode":{"text":"ERROR: Incorrect check sheet format."}},{"type":"decision","text":"Status of check sheet < Packed?","errorNode":{"text":"ERROR: Check sheet in incorrect status for packing."}},{"type":"decision","text":"Status of check sheet's Lot < Shipped?","errorNode":{"text":"ERROR: Lot in incorrect status for packing."}},{"type":"system","text":"Update screen to display Check Sheet No. and Lot No. as well as populating the list of open Tags","errorNode":null},{"type":"system","text":"Set check sheet status to Packing","errorNode":null},{"type":"system","text":"Set Order status to Packing","errorNode":null},{"type":"user","text":"Scan Contents Tag","errorNode":null},{"type":"decision","text":"Scanned value starts with \"T\"?","errorNode":{"text":"ERROR: Incorrect contents tag format."}},{"type":"decision","text":"Scanned value after \"T\" exists in EOX Content Tag table?","errorNode":{"text":"ERROR: Tag does not exist."}},{"type":"decision","text":"Tag's Check Sheet Ser No field = current check sheet?","errorNode":{"text":"ERROR: Invalid tag for check sheet."}},{"type":"decision","text":"Content tag Packed field set to False?","errorNode":{"text":"ERROR: Tag already packed."}},{"type":"system","text":"","errorNode":null},{"type":"user","text":"","errorNode":null},{"type":"decision","text":"","errorNode":{"text":""}},{"type":"decision","text":"","errorNode":{"text":""}},{"type":"decision","text":"","errorNode":{"text":""}},{"type":"decision","text":"","errorNode":{"text":""}},{"type":"user","text":"","errorNode":null},{"type":"decision","text":"","errorNode":{"text":""}}]